[
    {
        "id": 0,
        "lastUpdated": "2023-10-03",
        "aprPercentage30Day": 4.166945070478849
    },
    {
        "id": 38,
        "networkPenetration": 0.32412202060771234,
        "aprPercentage30Day": 4.2
    },
    {
        "id": 31,
        "networkPenetration": 0.09661120275407015,
        "aprPercentage30Day": 4.29
    },
    {
        "id": 35,
        "networkPenetration": 0.029701881469793683,
        "aprPercentage30Day": 4.2
    },
    {
        "id": 43,
        "networkPenetration": 0.0017977957876114657,
        "aprPercentage30Day": 4.2
    },
    {
        "id": 416543,
        "networkPenetration": 0.010766453895622655,
        "aprPercentage30Day": 4.29
    },
    {
        "id": 27,
        "networkPenetration": 0.01188768557699204,
        "aprPercentage30Day": 4.15
    }
]